{"resource_state": 3, "athlete": {"id": 65299557, "resource_state": 1}, "name": "Morning Ride", "distance": 42604.5, "moving_time": 3645, "elapsed_time": 3645, "total_elevation_gain": 0, "type": "Ride", "workout_type": 12, "id": 4250576756, "external_id": "2020-10-27-151714-FITNESS 248C-24-0.fit", "upload_id": 4547129328, "start_date": "2020-10-27T15:17:14Z", "start_date_local": "2020-10-27T08:17:14Z", "timezone": "(GMT-08:00) America/Los_Angeles", "utc_offset": -25200.0, "start_latlng": null, "end_latlng": null, "location_city": null, "location_state": null, "location_country": "United States", "start_latitude": null, "start_longitude": null, "achievement_count": 0, "kudos_count": 8, "comment_count": 0, "athlete_count": 1, "photo_count": 0, "map": {"id": "a4250576756", "polyline": "", "resource_state": 3}, "trainer": true, "commute": false, "manual": false, "private": false, "visibility": "everyone", "flagged": false, "gear_id": "b7842389", "from_accepted_tag": false, "upload_id_str": "4547129328", "average_speed": 11.688, "max_speed": 15.8, "average_watts": 200.0, "weighted_average_watts": 199, "kilojoules": 729.1, "device_watts": true, "has_heartrate": true, "average_heartrate": 129.8, "max_heartrate": 141.0, "heartrate_opt_out": false, "display_hide_heartrate_option": true, "max_watts": 310, "pr_count": 0, "total_photo_count": 0, "has_kudoed": false, "description": "", "calories": 729.0, "perceived_exertion": 4.0, "prefer_perceived_exertion": null, "segment_efforts": [], "splits_metric": [{"distance": 1000.1, "elapsed_time": 86, "elevation_difference": null, "moving_time": 86, "split": 1, "average_speed": 11.63, "average_grade_adjusted_speed": null, "average_heartrate": 126.15116279069767, "pace_zone": 0}, {"distance": 1009.6, "elapsed_time": 88, "elevation_difference": null, "moving_time": 88, "split": 2, "average_speed": 11.47, "average_grade_adjusted_speed": null, "average_heartrate": 124.06818181818181, "pace_zone": 0}, {"distance": 1000.0, "elapsed_time": 84, "elevation_difference": null, "moving_time": 84, "split": 3, "average_speed": 11.9, "average_grade_adjusted_speed": null, "average_heartrate": 124.89285714285714, "pace_zone": 0}, {"distance": 991.5, "elapsed_time": 86, "elevation_difference": null, "moving_time": 86, "split": 4, "average_speed": 11.53, "average_grade_adjusted_speed": null, "average_heartrate": 123.15116279069767, "pace_zone": 0}, {"distance": 999.6, "elapsed_time": 84, "elevation_difference": null, "moving_time": 84, "split": 5, "average_speed": 11.9, "average_grade_adjusted_speed": null, "average_heartrate": 126.03571428571429, "pace_zone": 0}, {"distance": 1006.9, "elapsed_time": 84, "elevation_difference": null, "moving_time": 84, "split": 6, "average_speed": 11.99, "average_grade_adjusted_speed": null, "average_heartrate": 126.94047619047619, "pace_zone": 0}, {"distance": 1002.1, "elapsed_time": 83, "elevation_difference": null, "moving_time": 83, "split": 7, "average_speed": 12.07, "average_grade_adjusted_speed": null, "average_heartrate": 126.40963855421687, "pace_zone": 0}, {"distance": 992.2, "elapsed_time": 81, "elevation_difference": null, "moving_time": 81, "split": 8, "average_speed": 12.25, "average_grade_adjusted_speed": null, "average_heartrate": 127.32098765432099, "pace_zone": 0}, {"distance": 1010.2, "elapsed_time": 82, "elevation_difference": null, "moving_time": 82, "split": 9, "average_speed": 12.32, "average_grade_adjusted_speed": null, "average_heartrate": 127.8170731707317, "pace_zone": 0}, {"distance": 1002.8, "elapsed_time": 81, "elevation_difference": null, "moving_time": 81, "split": 10, "average_speed": 12.38, "average_grade_adjusted_speed": null, "average_heartrate": 127.45679012345678, "pace_zone": 0}, {"distance": 991.6, "elapsed_time": 83, "elevation_difference": null, "moving_time": 83, "split": 11, "average_speed": 11.95, "average_grade_adjusted_speed": null, "average_heartrate": 127.97590361445783, "pace_zone": 0}, {"distance": 1000.2, "elapsed_time": 83, "elevation_difference": null, "moving_time": 83, "split": 12, "average_speed": 12.05, "average_grade_adjusted_speed": null, "average_heartrate": 127.81927710843374, "pace_zone": 0}, {"distance": 1001.1, "elapsed_time": 82, "elevation_difference": null, "moving_time": 82, "split": 13, "average_speed": 12.21, "average_grade_adjusted_speed": null, "average_heartrate": 127.79268292682927, "pace_zone": 0}, {"distance": 994.4, "elapsed_time": 81, "elevation_difference": null, "moving_time": 81, "split": 14, "average_speed": 12.28, "average_grade_adjusted_speed": null, "average_heartrate": 129.19753086419752, "pace_zone": 0}, {"distance": 998.3, "elapsed_time": 83, "elevation_difference": null, "moving_time": 83, "split": 15, "average_speed": 12.03, "average_grade_adjusted_speed": null, "average_heartrate": 128.34939759036143, "pace_zone": 0}, {"distance": 1004.4, "elapsed_time": 84, "elevation_difference": null, "moving_time": 84, "split": 16, "average_speed": 11.96, "average_grade_adjusted_speed": null, "average_heartrate": 130.29761904761904, "pace_zone": 0}, {"distance": 1003.1, "elapsed_time": 83, "elevation_difference": null, "moving_time": 83, "split": 17, "average_speed": 12.09, "average_grade_adjusted_speed": null, "average_heartrate": 130.03614457831324, "pace_zone": 0}, {"distance": 1000.1, "elapsed_time": 86, "elevation_difference": null, "moving_time": 86, "split": 18, "average_speed": 11.63, "average_grade_adjusted_speed": null, "average_heartrate": 128.1627906976744, "pace_zone": 0}, {"distance": 999.1, "elapsed_time": 86, "elevation_difference": null, "moving_time": 86, "split": 19, "average_speed": 11.62, "average_grade_adjusted_speed": null, "average_heartrate": 126.93023255813954, "pace_zone": 0}, {"distance": 1000.3, "elapsed_time": 85, "elevation_difference": null, "moving_time": 85, "split": 20, "average_speed": 11.77, "average_grade_adjusted_speed": null, "average_heartrate": 129.88235294117646, "pace_zone": 0}, {"distance": 992.8, "elapsed_time": 85, "elevation_difference": null, "moving_time": 85, "split": 21, "average_speed": 11.68, "average_grade_adjusted_speed": null, "average_heartrate": 129.9764705882353, "pace_zone": 0}, {"distance": 1009.0, "elapsed_time": 85, "elevation_difference": null, "moving_time": 85, "split": 22, "average_speed": 11.87, "average_grade_adjusted_speed": null, "average_heartrate": 129.98823529411766, "pace_zone": 0}, {"distance": 997.8, "elapsed_time": 86, "elevation_difference": null, "moving_time": 86, "split": 23, "average_speed": 11.6, "average_grade_adjusted_speed": null, "average_heartrate": 128.03488372093022, "pace_zone": 0}, {"distance": 999.6, "elapsed_time": 86, "elevation_difference": null, "moving_time": 86, "split": 24, "average_speed": 11.62, "average_grade_adjusted_speed": null, "average_heartrate": 130.04651162790697, "pace_zone": 0}, {"distance": 996.5, "elapsed_time": 86, "elevation_difference": null, "moving_time": 86, "split": 25, "average_speed": 11.59, "average_grade_adjusted_speed": null, "average_heartrate": 128.7906976744186, "pace_zone": 0}, {"distance": 1003.6, "elapsed_time": 86, "elevation_difference": null, "moving_time": 86, "split": 26, "average_speed": 11.67, "average_grade_adjusted_speed": null, "average_heartrate": 132.88372093023256, "pace_zone": 0}, {"distance": 996.9, "elapsed_time": 85, "elevation_difference": null, "moving_time": 85, "split": 27, "average_speed": 11.73, "average_grade_adjusted_speed": null, "average_heartrate": 128.47058823529412, "pace_zone": 0}, {"distance": 998.2, "elapsed_time": 88, "elevation_difference": null, "moving_time": 88, "split": 28, "average_speed": 11.34, "average_grade_adjusted_speed": null, "average_heartrate": 133.4090909090909, "pace_zone": 0}, {"distance": 1000.0, "elapsed_time": 85, "elevation_difference": null, "moving_time": 85, "split": 29, "average_speed": 11.76, "average_grade_adjusted_speed": null, "average_heartrate": 131.47058823529412, "pace_zone": 0}, {"distance": 1004.2, "elapsed_time": 86, "elevation_difference": null, "moving_time": 86, "split": 30, "average_speed": 11.68, "average_grade_adjusted_speed": null, "average_heartrate": 132.56976744186048, "pace_zone": 0}, {"distance": 995.3, "elapsed_time": 86, "elevation_difference": null, "moving_time": 86, "split": 31, "average_speed": 11.57, "average_grade_adjusted_speed": null, "average_heartrate": 132.48837209302326, "pace_zone": 0}, {"distance": 1004.7, "elapsed_time": 88, "elevation_difference": null, "moving_time": 88, "split": 32, "average_speed": 11.42, "average_grade_adjusted_speed": null, "average_heartrate": 130.64772727272728, "pace_zone": 0}, {"distance": 997.4, "elapsed_time": 88, "elevation_difference": null, "moving_time": 88, "split": 33, "average_speed": 11.33, "average_grade_adjusted_speed": null, "average_heartrate": 131.27272727272728, "pace_zone": 0}, {"distance": 999.0, "elapsed_time": 89, "elevation_difference": null, "moving_time": 89, "split": 34, "average_speed": 11.22, "average_grade_adjusted_speed": null, "average_heartrate": 132.97752808988764, "pace_zone": 0}, {"distance": 998.6, "elapsed_time": 88, "elevation_difference": null, "moving_time": 88, "split": 35, "average_speed": 11.35, "average_grade_adjusted_speed": null, "average_heartrate": 130.73863636363637, "pace_zone": 0}, {"distance": 1001.9, "elapsed_time": 88, "elevation_difference": null, "moving_time": 88, "split": 36, "average_speed": 11.39, "average_grade_adjusted_speed": null, "average_heartrate": 131.9318181818182, "pace_zone": 0}, {"distance": 997.2, "elapsed_time": 88, "elevation_difference": null, "moving_time": 88, "split": 37, "average_speed": 11.33, "average_grade_adjusted_speed": null, "average_heartrate": 130.51136363636363, "pace_zone": 0}, {"distance": 1003.1, "elapsed_time": 90, "elevation_difference": null, "moving_time": 90, "split": 38, "average_speed": 11.15, "average_grade_adjusted_speed": null, "average_heartrate": 131.88888888888889, "pace_zone": 0}, {"distance": 1005.2, "elapsed_time": 89, "elevation_difference": null, "moving_time": 89, "split": 39, "average_speed": 11.29, "average_grade_adjusted_speed": null, "average_heartrate": 132.76404494382024, "pace_zone": 0}, {"distance": 995.5, "elapsed_time": 85, "elevation_difference": null, "moving_time": 85, "split": 40, "average_speed": 11.71, "average_grade_adjusted_speed": null, "average_heartrate": 134.98823529411766, "pace_zone": 0}, {"distance": 997.2, "elapsed_time": 88, "elevation_difference": null, "moving_time": 88, "split": 41, "average_speed": 11.33, "average_grade_adjusted_speed": null, "average_heartrate": 134.875, "pace_zone": 0}, {"distance": 1004.3, "elapsed_time": 91, "elevation_difference": null, "moving_time": 91, "split": 42, "average_speed": 11.04, "average_grade_adjusted_speed": null, "average_heartrate": 137.1098901098901, "pace_zone": 0}, {"distance": 598.9, "elapsed_time": 54, "elevation_difference": null, "moving_time": 54, "split": 43, "average_speed": 11.09, "average_grade_adjusted_speed": null, "average_heartrate": 138.90740740740742, "pace_zone": 0}], "splits_standard": [{"distance": 1612.6, "elapsed_time": 140, "elevation_difference": null, "moving_time": 140, "split": 1, "average_speed": 11.52, "average_grade_adjusted_speed": null, "average_heartrate": 125.2, "pace_zone": 0}, {"distance": 1614.6, "elapsed_time": 137, "elevation_difference": null, "moving_time": 137, "split": 2, "average_speed": 11.79, "average_grade_adjusted_speed": null, "average_heartrate": 124.21167883211679, "pace_zone": 0}, {"distance": 1607.1, "elapsed_time": 137, "elevation_difference": null, "moving_time": 137, "split": 3, "average_speed": 11.73, "average_grade_adjusted_speed": null, "average_heartrate": 124.98540145985402, "pace_zone": 0}, {"distance": 1606.4, "elapsed_time": 134, "elevation_difference": null, "moving_time": 134, "split": 4, "average_speed": 11.99, "average_grade_adjusted_speed": null, "average_heartrate": 126.6268656716418, "pace_zone": 0}, {"distance": 1614.2, "elapsed_time": 132, "elevation_difference": null, "moving_time": 132, "split": 5, "average_speed": 12.23, "average_grade_adjusted_speed": null, "average_heartrate": 127.06060606060606, "pace_zone": 0}, {"distance": 1612.2, "elapsed_time": 130, "elevation_difference": null, "moving_time": 130, "split": 6, "average_speed": 12.4, "average_grade_adjusted_speed": null, "average_heartrate": 128.1, "pace_zone": 0}, {"distance": 1609.4, "elapsed_time": 134, "elevation_difference": null, "moving_time": 134, "split": 7, "average_speed": 12.01, "average_grade_adjusted_speed": null, "average_heartrate": 127.58208955223881, "pace_zone": 0}, {"distance": 1602.2, "elapsed_time": 134, "elevation_difference": null, "moving_time": 134, "split": 8, "average_speed": 11.96, "average_grade_adjusted_speed": null, "average_heartrate": 127.56716417910448, "pace_zone": 0}, {"distance": 1605.4, "elapsed_time": 130, "elevation_difference": null, "moving_time": 130, "split": 9, "average_speed": 12.35, "average_grade_adjusted_speed": null, "average_heartrate": 129.14615384615385, "pace_zone": 0}, {"distance": 1614.0, "elapsed_time": 134, "elevation_difference": null, "moving_time": 134, "split": 10, "average_speed": 12.04, "average_grade_adjusted_speed": null, "average_heartrate": 129.8582089552239, "pace_zone": 0}, {"distance": 1605.0, "elapsed_time": 136, "elevation_difference": null, "moving_time": 136, "split": 11, "average_speed": 11.8, "average_grade_adjusted_speed": null, "average_heartrate": 129.02205882352942, "pace_zone": 0}, {"distance": 1617.6, "elapsed_time": 139, "elevation_difference": null, "moving_time": 139, "split": 12, "average_speed": 11.64, "average_grade_adjusted_speed": null, "average_heartrate": 127.35971223021583, "pace_zone": 0}, {"distance": 1612.2, "elapsed_time": 137, "elevation_difference": null, "moving_time": 137, "split": 13, "average_speed": 11.77, "average_grade_adjusted_speed": null, "average_heartrate": 130.1897810218978, "pace_zone": 0}, {"distance": 1602.3, "elapsed_time": 136, "elevation_difference": null, "moving_time": 136, "split": 14, "average_speed": 11.78, "average_grade_adjusted_speed": null, "average_heartrate": 129.55882352941177, "pace_zone": 0}, {"distance": 1609.5, "elapsed_time": 139, "elevation_difference": null, "moving_time": 139, "split": 15, "average_speed": 11.58, "average_grade_adjusted_speed": null, "average_heartrate": 129.20143884892087, "pace_zone": 0}, {"distance": 1614.4, "elapsed_time": 139, "elevation_difference": null, "moving_time": 139, "split": 16, "average_speed": 11.61, "average_grade_adjusted_speed": null, "average_heartrate": 130.92805755395685, "pace_zone": 0}, {"distance": 1601.3, "elapsed_time": 138, "elevation_difference": null, "moving_time": 138, "split": 17, "average_speed": 11.6, "average_grade_adjusted_speed": null, "average_heartrate": 129.15217391304347, "pace_zone": 0}, {"distance": 1617.6, "elapsed_time": 139, "elevation_difference": null, "moving_time": 139, "split": 18, "average_speed": 11.64, "average_grade_adjusted_speed": null, "average_heartrate": 132.97841726618705, "pace_zone": 0}, {"distance": 1604.4, "elapsed_time": 139, "elevation_difference": null, "moving_time": 139, "split": 19, "average_speed": 11.54, "average_grade_adjusted_speed": null, "average_heartrate": 132.37410071942446, "pace_zone": 0}, {"distance": 1608.8, "elapsed_time": 139, "elevation_difference": null, "moving_time": 139, "split": 20, "average_speed": 11.57, "average_grade_adjusted_speed": null, "average_heartrate": 131.76258992805757, "pace_zone": 0}, {"distance": 1609.9, "elapsed_time": 143, "elevation_difference": null, "moving_time": 143, "split": 21, "average_speed": 11.26, "average_grade_adjusted_speed": null, "average_heartrate": 131.7902097902098, "pace_zone": 0}, {"distance": 1605.3, "elapsed_time": 141, "elevation_difference": null, "moving_time": 141, "split": 22, "average_speed": 11.39, "average_grade_adjusted_speed": null, "average_heartrate": 131.32624113475177, "pace_zone": 0}, {"distance": 1617.6, "elapsed_time": 143, "elevation_difference": null, "moving_time": 143, "split": 23, "average_speed": 11.31, "average_grade_adjusted_speed": null, "average_heartrate": 130.98601398601397, "pace_zone": 0}, {"distance": 1608.0, "elapsed_time": 144, "elevation_difference": null, "moving_time": 144, "split": 24, "average_speed": 11.17, "average_grade_adjusted_speed": null, "average_heartrate": 132.21527777777777, "pace_zone": 0}, {"distance": 1610.3, "elapsed_time": 139, "elevation_difference": null, "moving_time": 139, "split": 25, "average_speed": 11.58, "average_grade_adjusted_speed": null, "average_heartrate": 135.0, "pace_zone": 0}, {"distance": 1606.9, "elapsed_time": 144, "elevation_difference": null, "moving_time": 144, "split": 26, "average_speed": 11.16, "average_grade_adjusted_speed": null, "average_heartrate": 135.39583333333334, "pace_zone": 0}, {"distance": 755.3, "elapsed_time": 68, "elevation_difference": null, "moving_time": 68, "split": 27, "average_speed": 11.11, "average_grade_adjusted_speed": null, "average_heartrate": 138.94117647058823, "pace_zone": 0}], "laps": [{"id": 13913338619, "resource_state": 2, "name": "Lap 1", "activity": {"id": 4250576756, "resource_state": 1}, "athlete": {"id": 65299557, "resource_state": 1}, "elapsed_time": 3646, "moving_time": 3646, "start_date": "2020-10-27T15:17:14Z", "start_date_local": "2020-10-27T08:17:14Z", "distance": 42609.9, "start_index": 0, "end_index": 3645, "total_elevation_gain": 0, "average_speed": 11.69, "max_speed": 15.8, "device_watts": true, "average_watts": 200.0, "average_heartrate": 129.8, "max_heartrate": 141.0, "lap_index": 1, "split": 1}], "gear": {"id": "b7842389", "primary": true, "name": "Trek Domane AL 2", "resource_state": 2, "distance": 1908628}, "photos": {"primary": null, "count": 0}, "device_name": "Wahoo", "embed_token": "dc4c778fca98b9deb89f4d677451b1ca25d3ce5b", "available_zones": []}
