{"resource_state": 3, "athlete": {"id": 65299557, "resource_state": 1}, "name": "Morning Run", "distance": 1853.6, "moving_time": 813, "elapsed_time": 813, "total_elevation_gain": 31.0, "type": "Run", "sport_type": "Run", "workout_type": null, "id": 5131892807, "start_date": "2021-04-15T16:01:19Z", "start_date_local": "2021-04-15T09:01:19Z", "timezone": "(GMT-08:00) America/Los_Angeles", "utc_offset": -25200.0, "location_city": null, "location_state": null, "location_country": "United States", "achievement_count": 0, "kudos_count": 25, "comment_count": 0, "athlete_count": 1, "photo_count": 0, "map": {"id": "a5131892807", "polyline": "mdcaHd~shVRKTHNAd@OL?DD@LCl@ZJrA[^Cr@ORIt@MJAfAYz@s@X]`A}AV[d@]VYf@W^m@Ru@N[VI\\?HFJJp@rAZR`@Bx@W\\B`@Zp@P`@GZQVs@NAVNVCXQHSAWCMSIYa@WE[Dk@Wa@E_AHSG[[Qi@U]]SQ?[FWN]@YC]@QHe@h@c@ZELNtAEf@BHRC@FAHKLYR{@hAKR_A~@QZe@`@[d@i@j@oA\\s@XkALy@RMBMCWHc@FCACIIi@?YCIo@A[ES?", "resource_state": 3, "summary_polyline": "mdcaHd~shVRKTHNAd@OL?DD@LCl@ZJrA[^Cr@ORIt@MJAfAYz@s@X]`A}AV[d@]VYf@W^m@Ru@N[VI\\?HFJJp@rAZR`@Bx@W\\B`@Zp@P`@GZQVs@NAVNVCXQHSAWCMSIYa@WE[Dk@Wa@E_AHSG[[Qi@U]]SQ?[FWN]@YC]@QHe@h@c@ZELNtAEf@BHRC@FAHKLYR{@hAKR_A~@QZe@`@[d@i@j@oA\\s@XkALy@RMBMCWHc@FCACIIi@?YCIo@A[ES?"}, "trainer": false, "commute": false, "manual": false, "private": false, "visibility": "everyone", "flagged": false, "gear_id": "g8242064", "start_latlng": [47.534958, -122.168183], "end_latlng": [47.534932, -122.168026], "average_speed": 2.28, "max_speed": 3.5, "average_cadence": 77.0, "average_temp": 26, "has_heartrate": true, "average_heartrate": 138.2, "max_heartrate": 158.0, "heartrate_opt_out": false, "display_hide_heartrate_option": true, "elev_high": 132.0, "elev_low": 119.6, "upload_id": 5470222273, "upload_id_str": "5470222273", "external_id": "garmin_push_6611731132", "from_accepted_tag": false, "pr_count": 0, "total_photo_count": 0, "has_kudoed": false, "suffer_score": 5.0, "description": null, "calories": 148.0, "perceived_exertion": null, "prefer_perceived_exertion": null, "segment_efforts": [], "splits_metric": [{"distance": 1004.6, "elapsed_time": 450, "elevation_difference": 4.2, "moving_time": 450, "split": 1, "average_speed": 2.23, "average_grade_adjusted_speed": 2.34, "average_heartrate": 131.84409799554567, "pace_zone": 0}, {"distance": 849.0, "elapsed_time": 363, "elevation_difference": -3.8, "moving_time": 363, "split": 2, "average_speed": 2.34, "average_grade_adjusted_speed": 2.4, "average_heartrate": 145.9504132231405, "pace_zone": 0}], "splits_standard": [{"distance": 1611.1, "elapsed_time": 713, "elevation_difference": 7.6, "moving_time": 713, "split": 1, "average_speed": 2.26, "average_grade_adjusted_speed": 2.37, "average_heartrate": 136.65870786516854, "pace_zone": 0}, {"distance": 242.5, "elapsed_time": 100, "elevation_difference": -7.2, "moving_time": 100, "split": 2, "average_speed": 2.43, "average_grade_adjusted_speed": 2.31, "average_heartrate": 148.77, "pace_zone": 0}], "laps": [{"id": 16737844893, "resource_state": 2, "name": "Lap 1", "activity": {"id": 5131892807, "resource_state": 1}, "athlete": {"id": 65299557, "resource_state": 1}, "elapsed_time": 712, "moving_time": 712, "start_date": "2021-04-15T16:01:19Z", "start_date_local": "2021-04-15T09:01:19Z", "distance": 1609.34, "start_index": 0, "end_index": 188, "total_elevation_gain": 31.0, "average_speed": 2.26, "max_speed": 3.1, "average_cadence": 77.2, "device_watts": false, "average_heartrate": 136.7, "max_heartrate": 158.0, "lap_index": 1, "split": 1, "pace_zone": 0}, {"id": 16737844899, "resource_state": 2, "name": "Lap 2", "activity": {"id": 5131892807, "resource_state": 1}, "athlete": {"id": 65299557, "resource_state": 1}, "elapsed_time": 100, "moving_time": 100, "start_date": "2021-04-15T16:13:17Z", "start_date_local": "2021-04-15T09:13:17Z", "distance": 244.23, "start_index": 189, "end_index": 216, "total_elevation_gain": 0.0, "average_speed": 2.44, "max_speed": 3.5, "average_cadence": 75.7, "device_watts": false, "average_heartrate": 148.7, "max_heartrate": 153.0, "lap_index": 2, "split": 2, "pace_zone": 0}], "best_efforts": [{"id": 10738213334, "resource_state": 2, "name": "400m", "activity": {"id": 5131892807, "resource_state": 1}, "athlete": {"id": 65299557, "resource_state": 1}, "elapsed_time": 166, "moving_time": 167, "start_date": "2021-04-15T16:11:56Z", "start_date_local": "2021-04-15T09:11:56Z", "distance": 400, "start_index": 163, "end_index": 213, "pr_rank": null, "achievements": []}, {"id": 10738213342, "resource_state": 2, "name": "1/2 mile", "activity": {"id": 5131892807, "resource_state": 1}, "athlete": {"id": 65299557, "resource_state": 1}, "elapsed_time": 344, "moving_time": 344, "start_date": "2021-04-15T16:08:42Z", "start_date_local": "2021-04-15T09:08:42Z", "distance": 805, "start_index": 108, "end_index": 207, "pr_rank": null, "achievements": []}, {"id": 10738213354, "resource_state": 2, "name": "1k", "activity": {"id": 5131892807, "resource_state": 1}, "athlete": {"id": 65299557, "resource_state": 1}, "elapsed_time": 429, "moving_time": 431, "start_date": "2021-04-15T16:07:18Z", "start_date_local": "2021-04-15T09:07:18Z", "distance": 1000, "start_index": 86, "end_index": 209, "pr_rank": null, "achievements": []}, {"id": 10738213369, "resource_state": 2, "name": "1 mile", "activity": {"id": 5131892807, "resource_state": 1}, "athlete": {"id": 65299557, "resource_state": 1}, "elapsed_time": 697, "moving_time": 698, "start_date": "2021-04-15T16:02:49Z", "start_date_local": "2021-04-15T09:02:49Z", "distance": 1609, "start_index": 27, "end_index": 208, "pr_rank": null, "achievements": []}], "gear": {"id": "g8242064", "primary": false, "name": "ASICS Gel Venture 5 Trail", "nickname": "", "resource_state": 2, "retired": true, "distance": 296989, "converted_distance": 184.5}, "photos": {"primary": null, "count": 0}, "stats_visibility": [{"type": "heart_rate", "visibility": "everyone"}, {"type": "pace", "visibility": "everyone"}, {"type": "power", "visibility": "everyone"}, {"type": "speed", "visibility": "everyone"}, {"type": "calories", "visibility": "everyone"}], "hide_from_home": false, "device_name": "Garmin Forerunner 945", "embed_token": "851351027a679e75de51234541d6626dc20a4285", "similar_activities": {"effort_count": 21, "average_speed": 2.533968859521028, "min_average_speed": 2.279950769478398, "mid_average_speed": 2.75410293447827, "max_average_speed": 3.477253271274812, "pr_rank": null, "frequency_milestone": null, "trend": {"speeds": [2.52456203016075, 2.4340308073838024, 2.3538181443426205, 2.2976398741160216, 2.3097253069126222], "current_activity_index": 2, "min_speed": 2.279950769478398, "mid_speed": 2.75410293447827, "max_speed": 3.477253271274812, "direction": 0}, "resource_state": 2}, "available_zones": ["heartrate", "pace"]}
