{"resource_state": 3, "athlete": {"id": 65299557, "resource_state": 1}, "name": "Morning Run", "distance": 8054.4, "moving_time": 3211, "elapsed_time": 3211, "total_elevation_gain": 20.0, "type": "Run", "sport_type": "Run", "workout_type": 0, "id": 6554703312, "start_date": "2022-01-20T17:01:17Z", "start_date_local": "2022-01-20T09:01:17Z", "timezone": "(GMT-08:00) America/Los_Angeles", "utc_offset": -28800.0, "location_city": null, "location_state": null, "location_country": "United States", "achievement_count": 0, "kudos_count": 20, "comment_count": 0, "athlete_count": 1, "photo_count": 0, "map": {"id": "a6554703312", "polyline": "iau`H~sbiVn@OP?t@On@?hAEXG|@AhBJNC`A?b@EZ?ND`@B^Ih@Af@MRCvBI`AHd@?^Ar@Qb@@tA@r@ERI`AMrDSdA?`@ChBAjAEn@@nCIBAb@@ZGX@h@EpBBx@UpAAf@E~ABj@?h@G`@Bd@Ef@I`@?n@GZB^?z@M~@ErBCpAG`AOzBD|@ClAI`ABxBMrABjA?fBGfAIlEOzC?b@CrD@nBEb@@bA?h@@p@HvC@b@DfA@~AAv@BRDzDDbAFb@CtAAt@Fn@?b@FdABdBAzDHf@@h@C`DLh@MrADdAHxB@hBCbABf@?rAIl@@pBMp@@?A{@Je@AiDT_A?e@Be@A{@B{BCy@BwAEa@@_@Fi@GqACmCKkIKgAE}EEoHOo@@}AAUCeBAa@Eg@@[E{@BoAEqA?qCKkB?wADwBEaADaC@UDaABi@A]DeEFaBJiA?]D{B@e@DiABgEPiB?qAHe@Lg@@gAJyD?qBB_BF]?cGXuCBa@BkBAs@DkA?mBHu@@kBJ_@Bi@NmCN}BCq@FsAB[Bi@Bc@H]@_@Me@CyABc@HoCFaALgA@iALaAB", "resource_state": 3, "summary_polyline": "iau`H~sbiVn@OP?t@On@?hAEXG|@AhBJNC`A?b@EZ?ND`@B^Ih@Af@MRCvBI`AHd@?^Ar@Qb@@tA@r@ERI`AMrDSdA?`@ChBAjAEn@@nCIBAb@@ZGX@h@EpBBx@UpAAf@E~ABj@?h@G`@Bd@Ef@I`@?n@GZB^?z@M~@ErBCpAG`AOzBD|@ClAI`ABxBMrABjA?fBGfAIlEOzC?b@CrD@nBEb@@bA?h@@p@HvC@b@DfA@~AAv@BRDzDDbAFb@CtAAt@Fn@?b@FdABdBAzDHf@@h@C`DLh@MrADdAHxB@hBCbABf@?rAIl@@pBMp@@?A{@Je@AiDT_A?e@Be@A{@B{BCy@BwAEa@@_@Fi@GqACmCKkIKgAE}EEoHOo@@}AAUCeBAa@Eg@@[E{@BoAEqA?qCKkB?wADwBEaADaC@UDaABi@A]DeEFaBJiA?]D{B@e@DiABgEPiB?qAHe@Lg@@gAJyD?qBB_BF]?cGXuCBa@BkBAs@DkA?mBHu@@kBJ_@Bi@NmCN}BCq@FsAB[Bi@Bc@H]@_@Me@CyABc@HoCFaALgA@iALaAB"}, "trainer": false, "commute": false, "manual": false, "private": false, "visibility": "everyone", "flagged": false, "gear_id": "g9932645", "start_latlng": [47.462777411565185, -122.24335986189544], "end_latlng": [47.462233090773225, -122.24329096265137], "average_speed": 2.508, "max_speed": 3.441, "average_cadence": 76.5, "average_temp": 22, "has_heartrate": true, "average_heartrate": 131.2, "max_heartrate": 139.0, "heartrate_opt_out": false, "display_hide_heartrate_option": true, "elev_high": 7.6, "elev_low": -2.0, "upload_id": 6969821921, "upload_id_str": "6969821921", "external_id": "garmin_push_8152423337", "from_accepted_tag": false, "pr_count": 0, "total_photo_count": 0, "has_kudoed": false, "suffer_score": 13.0, "description": "", "calories": 619.0, "perceived_exertion": null, "prefer_perceived_exertion": false, "segment_efforts": [{"id": 2919311989671341122, "resource_state": 2, "name": "180th to 196th", "activity": {"id": 6554703312, "resource_state": 1}, "athlete": {"id": 65299557, "resource_state": 1}, "elapsed_time": 637, "moving_time": 637, "start_date": "2022-01-20T17:17:06Z", "start_date_local": "2022-01-20T09:17:06Z", "distance": 1598.2, "start_index": 178, "end_index": 293, "average_cadence": 76.0, "device_watts": false, "average_heartrate": 131.1, "max_heartrate": 136.0, "segment": {"id": 17391139, "resource_state": 2, "name": "180th to 196th", "activity_type": "Run", "distance": 1598.2, "average_grade": -0.1, "maximum_grade": 0.3, "elevation_high": 10.0, "elevation_low": 8.6, "start_latlng": [47.441104, -122.241767], "end_latlng": [47.426733, -122.242167], "elevation_profile": null, "climb_category": 0, "city": "Tukwila", "state": "Washington", "country": "United States", "private": false, "hazardous": false, "starred": false}, "pr_rank": null, "achievements": [{"type_id": 7, "type": "segment_effort_count_leader", "rank": 1, "effort_count": 5}], "kom_rank": null, "hidden": false}, {"id": 2919311989672950850, "resource_state": 2, "name": "IUT 196th to Longacre", "activity": {"id": 6554703312, "resource_state": 1}, "athlete": {"id": 65299557, "resource_state": 1}, "elapsed_time": 1322, "moving_time": 1322, "start_date": "2022-01-20T17:28:33Z", "start_date_local": "2022-01-20T09:28:33Z", "distance": 3307.5, "start_index": 303, "end_index": 548, "average_cadence": 76.4, "device_watts": false, "average_heartrate": 132.8, "max_heartrate": 138.0, "segment": {"id": 15694438, "resource_state": 2, "name": "IUT 196th to Longacre", "activity_type": "Run", "distance": 3307.5, "average_grade": -0.0, "maximum_grade": 1.3, "elevation_high": 10.0, "elevation_low": 7.7, "start_latlng": [47.42699, -122.24223], "end_latlng": [47.456599, -122.242875], "elevation_profile": null, "climb_category": 0, "city": null, "state": null, "country": null, "private": false, "hazardous": false, "starred": false}, "pr_rank": null, "achievements": [{"type_id": 7, "type": "segment_effort_count_leader", "rank": 1, "effort_count": 6}], "kom_rank": null, "hidden": false}, {"id": 2919311989671444546, "resource_state": 2, "name": "Interurban Trail - 180th to Longacres", "activity": {"id": 6554703312, "resource_state": 1}, "athlete": {"id": 65299557, "resource_state": 1}, "elapsed_time": 858, "moving_time": 858, "start_date": "2022-01-20T17:39:28Z", "start_date_local": "2022-01-20T09:39:28Z", "distance": 2172.8, "start_index": 419, "end_index": 581, "average_cadence": 76.6, "device_watts": false, "average_heartrate": 133.8, "max_heartrate": 138.0, "segment": {"id": 7031050, "resource_state": 2, "name": "Interurban Trail - 180th to Longacres", "activity_type": "Run", "distance": 2172.8, "average_grade": -0.1, "maximum_grade": 15.3, "elevation_high": -7.2, "elevation_low": -12.8, "start_latlng": [47.441444, -122.241744], "end_latlng": [47.460886, -122.243192], "elevation_profile": null, "climb_category": 0, "city": "Kent", "state": "WA", "country": "United States", "private": false, "hazardous": false, "starred": false}, "pr_rank": null, "achievements": [{"type_id": 7, "type": "segment_effort_count_leader", "rank": 1, "effort_count": 7}], "kom_rank": null, "hidden": false}], "splits_metric": [{"distance": 1014.3, "elapsed_time": 410, "elevation_difference": -1.2, "moving_time": 410, "split": 1, "average_speed": 2.47, "average_grade_adjusted_speed": 2.48, "average_heartrate": 124.20975609756097, "pace_zone": 0}, {"distance": 1007.0, "elapsed_time": 394, "elevation_difference": -1.4, "moving_time": 394, "split": 2, "average_speed": 2.56, "average_grade_adjusted_speed": 2.56, "average_heartrate": 131.5964467005076, "pace_zone": 0}, {"distance": 982.3, "elapsed_time": 383, "elevation_difference": -2.8, "moving_time": 383, "split": 3, "average_speed": 2.56, "average_grade_adjusted_speed": 2.56, "average_heartrate": 132.53524804177545, "pace_zone": 0}, {"distance": 1014.4, "elapsed_time": 406, "elevation_difference": -3.2, "moving_time": 406, "split": 4, "average_speed": 2.5, "average_grade_adjusted_speed": 2.49, "average_heartrate": 130.08128078817734, "pace_zone": 0}, {"distance": 995.0, "elapsed_time": 401, "elevation_difference": 1.8, "moving_time": 401, "split": 5, "average_speed": 2.48, "average_grade_adjusted_speed": 2.5, "average_heartrate": 130.40100250626566, "pace_zone": 0}, {"distance": 987.5, "elapsed_time": 397, "elevation_difference": 4.4, "moving_time": 397, "split": 6, "average_speed": 2.49, "average_grade_adjusted_speed": 2.53, "average_heartrate": 132.8110831234257, "pace_zone": 0}, {"distance": 1011.9, "elapsed_time": 402, "elevation_difference": 0.8, "moving_time": 402, "split": 7, "average_speed": 2.52, "average_grade_adjusted_speed": 2.53, "average_heartrate": 134.76119402985074, "pace_zone": 0}, {"distance": 1005.0, "elapsed_time": 403, "elevation_difference": -4.0, "moving_time": 403, "split": 8, "average_speed": 2.49, "average_grade_adjusted_speed": 2.49, "average_heartrate": 133.29280397022333, "pace_zone": 0}, {"distance": 37.0, "elapsed_time": 15, "elevation_difference": 0.8, "moving_time": 15, "split": 9, "average_speed": 2.47, "average_grade_adjusted_speed": 2.62, "average_heartrate": 133.0, "pace_zone": 0}], "splits_standard": [{"distance": 1611.5, "elapsed_time": 646, "elevation_difference": -2.8, "moving_time": 646, "split": 1, "average_speed": 2.49, "average_grade_adjusted_speed": 2.5, "average_heartrate": 126.44736842105263, "pace_zone": 0}, {"distance": 1609.3, "elapsed_time": 629, "elevation_difference": -4.4, "moving_time": 629, "split": 2, "average_speed": 2.56, "average_grade_adjusted_speed": 2.55, "average_heartrate": 132.40858505564387, "pace_zone": 0}, {"distance": 1608.0, "elapsed_time": 647, "elevation_difference": 0.0, "moving_time": 647, "split": 3, "average_speed": 2.49, "average_grade_adjusted_speed": 2.49, "average_heartrate": 130.15813953488373, "pace_zone": 0}, {"distance": 1609.4, "elapsed_time": 642, "elevation_difference": 5.0, "moving_time": 642, "split": 4, "average_speed": 2.51, "average_grade_adjusted_speed": 2.54, "average_heartrate": 133.4423676012461, "pace_zone": 0}, {"distance": 1610.5, "elapsed_time": 645, "elevation_difference": -2.8, "moving_time": 645, "split": 5, "average_speed": 2.5, "average_grade_adjusted_speed": 2.5, "average_heartrate": 133.53953488372093, "pace_zone": 0}, {"distance": 5.7, "elapsed_time": 2, "elevation_difference": 0.2, "moving_time": 2, "split": 6, "average_speed": 2.85, "average_grade_adjusted_speed": 3.05, "average_heartrate": 133.0, "pace_zone": 0}], "laps": [{"id": 21468021830, "resource_state": 2, "name": "Lap 1", "activity": {"id": 6554703312, "resource_state": 1}, "athlete": {"id": 65299557, "resource_state": 1}, "elapsed_time": 646, "moving_time": 646, "start_date": "2022-01-20T17:01:17Z", "start_date_local": "2022-01-20T09:01:17Z", "distance": 1609.34, "start_index": 0, "end_index": 127, "total_elevation_gain": 5.6, "average_speed": 2.49, "max_speed": 2.99, "average_cadence": 77.6, "device_watts": false, "average_heartrate": 126.4, "max_heartrate": 134.0, "lap_index": 1, "split": 1, "pace_zone": 0}, {"id": 21468021833, "resource_state": 2, "name": "Lap 2", "activity": {"id": 6554703312, "resource_state": 1}, "athlete": {"id": 65299557, "resource_state": 1}, "elapsed_time": 628, "moving_time": 628, "start_date": "2022-01-20T17:12:07Z", "start_date_local": "2022-01-20T09:12:07Z", "distance": 1609.34, "start_index": 128, "end_index": 241, "total_elevation_gain": 0.0, "average_speed": 2.56, "max_speed": 2.957, "average_cadence": 75.7, "device_watts": false, "average_heartrate": 132.4, "max_heartrate": 139.0, "lap_index": 2, "split": 2, "pace_zone": 0}, {"id": 21468021835, "resource_state": 2, "name": "Lap 3", "activity": {"id": 6554703312, "resource_state": 1}, "athlete": {"id": 65299557, "resource_state": 1}, "elapsed_time": 647, "moving_time": 647, "start_date": "2022-01-20T17:22:35Z", "start_date_local": "2022-01-20T09:22:35Z", "distance": 1609.34, "start_index": 242, "end_index": 353, "total_elevation_gain": 2.0, "average_speed": 2.49, "max_speed": 3.441, "average_cadence": 76.2, "device_watts": false, "average_heartrate": 130.2, "max_heartrate": 136.0, "lap_index": 3, "split": 3, "pace_zone": 0}, {"id": 21468021837, "resource_state": 2, "name": "Lap 4", "activity": {"id": 6554703312, "resource_state": 1}, "athlete": {"id": 65299557, "resource_state": 1}, "elapsed_time": 641, "moving_time": 641, "start_date": "2022-01-20T17:33:27Z", "start_date_local": "2022-01-20T09:33:27Z", "distance": 1609.34, "start_index": 354, "end_index": 473, "total_elevation_gain": 11.4, "average_speed": 2.51, "max_speed": 2.76, "average_cadence": 76.4, "device_watts": false, "average_heartrate": 133.5, "max_heartrate": 137.0, "lap_index": 4, "split": 4, "pace_zone": 0}, {"id": 21468021840, "resource_state": 2, "name": "Lap 5", "activity": {"id": 6554703312, "resource_state": 1}, "athlete": {"id": 65299557, "resource_state": 1}, "elapsed_time": 644, "moving_time": 644, "start_date": "2022-01-20T17:44:05Z", "start_date_local": "2022-01-20T09:44:05Z", "distance": 1609.34, "start_index": 474, "end_index": 590, "total_elevation_gain": 2.4, "average_speed": 2.5, "max_speed": 2.819, "average_cadence": 76.6, "device_watts": false, "average_heartrate": 133.5, "max_heartrate": 138.0, "lap_index": 5, "split": 5, "pace_zone": 0}], "best_efforts": [{"id": 16506545031, "resource_state": 2, "name": "400m", "activity": {"id": 6554703312, "resource_state": 1}, "athlete": {"id": 65299557, "resource_state": 1}, "elapsed_time": 154, "moving_time": 155, "start_date": "2022-01-20T17:07:37Z", "start_date_local": "2022-01-20T09:07:37Z", "distance": 400, "start_index": 75, "end_index": 104, "pr_rank": null, "achievements": []}, {"id": 16506545053, "resource_state": 2, "name": "1/2 mile", "activity": {"id": 6554703312, "resource_state": 1}, "athlete": {"id": 65299557, "resource_state": 1}, "elapsed_time": 312, "moving_time": 313, "start_date": "2022-01-20T17:12:00Z", "start_date_local": "2022-01-20T09:12:00Z", "distance": 805, "start_index": 126, "end_index": 179, "pr_rank": null, "achievements": []}, {"id": 16506545076, "resource_state": 2, "name": "1k", "activity": {"id": 6554703312, "resource_state": 1}, "athlete": {"id": 65299557, "resource_state": 1}, "elapsed_time": 388, "moving_time": 389, "start_date": "2022-01-20T17:11:52Z", "start_date_local": "2022-01-20T09:11:52Z", "distance": 1000, "start_index": 125, "end_index": 192, "pr_rank": null, "achievements": []}, {"id": 16506545091, "resource_state": 2, "name": "1 mile", "activity": {"id": 6554703312, "resource_state": 1}, "athlete": {"id": 65299557, "resource_state": 1}, "elapsed_time": 626, "moving_time": 627, "start_date": "2022-01-20T17:09:11Z", "start_date_local": "2022-01-20T09:09:11Z", "distance": 1609, "start_index": 93, "end_index": 206, "pr_rank": null, "achievements": []}, {"id": 16506545112, "resource_state": 2, "name": "2 mile", "activity": {"id": 6554703312, "resource_state": 1}, "athlete": {"id": 65299557, "resource_state": 1}, "elapsed_time": 1266, "moving_time": 1268, "start_date": "2022-01-20T17:07:27Z", "start_date_local": "2022-01-20T09:07:27Z", "distance": 3219, "start_index": 73, "end_index": 304, "pr_rank": null, "achievements": []}, {"id": 16506545126, "resource_state": 2, "name": "5k", "activity": {"id": 6554703312, "resource_state": 1}, "athlete": {"id": 65299557, "resource_state": 1}, "elapsed_time": 1984, "moving_time": 1985, "start_date": "2022-01-20T17:04:38Z", "start_date_local": "2022-01-20T09:04:38Z", "distance": 5000, "start_index": 43, "end_index": 401, "pr_rank": null, "achievements": []}], "gear": {"id": "g9932645", "primary": false, "name": "Brooks Glycerin 19", "nickname": null, "resource_state": 2, "retired": true, "distance": 428309, "converted_distance": 266.1}, "photos": {"primary": null, "count": 0}, "stats_visibility": [{"type": "heart_rate", "visibility": "everyone"}, {"type": "pace", "visibility": "everyone"}, {"type": "power", "visibility": "everyone"}, {"type": "speed", "visibility": "everyone"}, {"type": "calories", "visibility": "everyone"}], "hide_from_home": false, "device_name": "Garmin Forerunner 945", "embed_token": "9d6955be75a1c4c1200779eaa56f7f78ce5a0e8d", "similar_activities": {"effort_count": 10, "average_speed": 2.718957885060692, "min_average_speed": 2.4126168074008234, "mid_average_speed": 2.871343548193625, "max_average_speed": 3.545466463330766, "pr_rank": null, "frequency_milestone": null, "trend": {"speeds": [2.755374181200884, 2.525020066871258, 2.5731342623484226, 2.520446918991189, 2.6284632521613376], "current_activity_index": 3, "min_speed": 2.4126168074008234, "mid_speed": 2.871343548193625, "max_speed": 3.545466463330766, "direction": 0}, "resource_state": 2}, "available_zones": ["heartrate", "pace"]}
